an_uniqueenvvar/__init__.py
an_uniqueenvvar/uniqueenvvar.py
an_uniqueenvvar-0.1.5.dist-info/licenses/LICENSE
an_uniqueenvvar-0.1.5.dist-info/METADATA
an_uniqueenvvar-0.1.5.dist-info/WHEEL
an_uniqueenvvar-0.1.5.dist-info/top_level.txt
an_uniqueenvvar-0.1.5.dist-info/RECORD
