Metadata-Version: 2.4
Name: an_uniqueenvvar
Version: 0.1.5
Summary: A package for an_uniqueenvvar.
Home-page: https://github.com/Atsushi888/Atsushi888
Author: Atsushi888
Author-email: Atsushi888 <vtgrotxu@gmail.com>
Project-URL: Homepage, https://github.com/Atsushi888/an_uniqueenvvar
Project-URL: Repository, https://github.com/Atsushi888/an_uniqueenvvar
Requires-Python: >=3.6
License-File: LICENSE
Dynamic: author
Dynamic: home-page
Dynamic: license-file
Dynamic: requires-python
